[
  {
    "location": "Madrid",
    "date": "2026-05-21",
    "temp_max": 29.51300048828125,
    "temp_min": 13.21299934387207,
    "precipitation": 0.0,
    "wind": 6.877789497375488,
    "daylight": 52478.4296875,
    "uv": 7.949999809265137
  },
  {
    "location": "Vienna",
    "date": "2026-05-21",
    "temp_max": 22.961000442504883,
    "temp_min": 12.81100082397461,
    "precipitation": 0.0,
    "wind": 21.434364318847656,
    "daylight": 55453.5390625,
    "uv": 6.550000190734863
  },
  {
    "location": "Aalborg",
    "date": "2026-05-21",
    "temp_max": 15.354499816894531,
    "temp_min": 11.104499816894531,
    "precipitation": 6.5,
    "wind": 16.19999885559082,
    "daylight": 60587.61328125,
    "uv": 2.5
  }
]